<routes><route id="12" town="Town13"><weathers><weathis_juncer route_percentage="0.0" cloudiness="5.0" precipitation="0.0" precipitation_deposits="0.0" wetness="0.0" wind_intensity="10.0" sun_azimuth_angle="-1.0" sun_altitude_angle="45.0" fog_density="2.0"/><weather route_percentage="100.0" cloudiness="5.0" precipitation="0.0" precipitation_deposits="0.0" wetness="0.0" wind_intensity="10.0" sun_azimuth_angle="-1.0" sun_altitude_angle="45.0" fog_density="2.0"/></weathers><waypoints><position x="3145.4" y="5334.3" z="173.3"/><position x="3102.4" y="5414.6" z="170.6"/></waypoints><scenarios><scenario name="BlockedIntersection_9" type="BlockedIntersection">
            <trigger_point x="3144.9" y="5354.6" z="172.8" yaw="91.2"/>
         </scenario>
         </scenarios></route></routes>