<routes><route id="27" town="Town12"><weathers><weathis_juncer cloudiness="5.0" fog_density="2.0" precipitation="0.0" precipitation_deposits="0.0" route_percentage="0.0" sun_altitude_angle="45.0" sun_azimuth_angle="-1.0" wetness="0.0" wind_intensity="10.0" /><weather cloudiness="5.0" fog_density="2.0" precipitation="0.0" precipitation_deposits="0.0" route_percentage="100.0" sun_altitude_angle="45.0" sun_azimuth_angle="-1.0" wetness="0.0" wind_intensity="10.0" /></weathers><waypoints><position x="-1798.1" y="6510.2" z="372.3" /><position x="-2182.3" y="6425.5" z="377.8" /></waypoints><scenarios><scenario name="YieldToEmergencyVehicle_1" type="YieldToEmergencyVehicle">
            <trigger_point x="-1817.8" y="6515.3" yaw="166.5" z="372.7" />
            <distance value="130" />
         </scenario>
         </scenarios></route></routes>